{
  "time": "2020-10-20 07:28:52",
  "begin": "2020-01-03",
  "end": "2020-02-02",
  "category": "보건복지",
  "title": "한부모 차량 자격 완화 부탁드립니다.",
  "content": "안녕하세요. 이혼으로 인해 2살 된 아이와 지내는 한부모 가정입니다. 한부모 자격 중 10년 이상, 1600cc미만, 150만원 미만인 차량만 타고 다닐 수 있다고 합니다. 그런 차가 있긴 한걸 까요?...현실적으로요. 지금 정부에서 경유 차량을 수도권에서 집중 단속 하고 있는데..10년 이상 된 차는 거의 90%이상이 경유 차량이예요.. 저는 지금 지방에 살고 있지만.. 몇년후면 지방도 단속 하겠지요.. 그렇다면 10년이상 된 차량은 타고 다닐 수도 없겠죠.. 설령 몇년 밖에 타지 못할 걸 각오하고 알아본들 150만원 미만인 차량은 어디에도 없더라구요.. cc야 경차를 타고 다니면 된다고 하지만 현실적으로 10년 이상 150만원 미만인 차량은 없어요.. 있다고 해서 타고 다니다 사고라도 나면 그냥 아이와 함께 죽으라는 겁니다. 지금 한부모 차량을 가지고 계신분들 차가 자주 고장나서 몇십만원 주고 고치고 타고 다니세요.. 왜냐면 아이가 새벽에 아프면, 병원가야되서. 밤늦게까지 일하게 되면 아이 데리러 가야되서. 버스는 언제 올지 모르구요. 택시는 한번 가는데 적게는 만원에서 많게는 이만원 정도 해요. 매번 이 비용을 감당하기에는 현실적으로 너무 힘듭니다. 저희 차 살돈 없서서 빚내서 사요..그 빚 내는 돈도 많이 감당못해요. 그래서 suv나 승용차는 꿈도 못꿔요.. 유지비도 많이 들어서 그냥 포기합니다. 단지, 그냥 10년 이상 150만원 미만 이라는 부분만 완화해주세요. 더 바라지도 않구요. 아이 키우려면 차는 필수구요. 좋은 차 감당 못해요.. 5년 이상 3-500만원 가액 차량으로 완화 시켜주시면 안되나요? 제발 부탁드립니다.",
  "keyword": [],
  "agree": 277,
  "status": "청원종료"
}