{
  "time": "2020-10-20 04:56:24",
  "begin": "2020-02-25",
  "end": "2020-03-26",
  "category": "보건복지",
  "title": "가능한 전사원 재택근무를 진심으로 요청합니다.",
  "content": "정부와 기업대표님들께 호소합니다. 재택 근무 반드시 해야합니다. 한 사무실에 다수의 인원이 오랜 시간 모여있는 것은 현시점에서 지양해야 합니다. 이것은 개인의 문제가 아닙니다. 임산부 노약자로 구분하는 것은 효용이 없습니다. 그들의 남편이 아내가 또 다른 직장에서 집으로 돌아오기 때문입니다. 만약 직원들이 위험지역 다녀왔는지 알아본다 해도 별반 소용이 없습니다. 자녀들 학교와 원내, 친구, 선생님들, 지인 그리고 그들의 지인까지 고려해야 한다면 끝이 없습니다. 직원들을 쓰러질지 모르는 도미노에서 빗겨가게 해주십시요. 그래야 그 뒤의 더많은 이들이 버틸 수 있고 병상을 확보할 수 있습니다. 나아가 의료진과 검역조사관, 애쓰는 모든 이들의 노력을 아낄 수 있습니다. 한명의 연결고리라도 더 끊어야 더 많은 안전과 병상을 확보할 수 있습니다. 사내망이 안 되면 개인 이메일과 휴대전화 영상 통화 가능한 모든 방법을 동원해 주십시요. 사내 데스크탑이라도 떼어가게 허락해 주십시요. 직원들을 믿어주십시요. 출퇴근 시간까지 합해서라도 일하겠습니다. 사업주의 배려에 직원들은 반드시 더 크게 보답할 것입니다. 사내 전기 수도료, 유지비 절감 및 출퇴근 스트레스 감소로 인한 업무 효율개선, 미세먼지 개선 등 장점도 고려해주십시요. 뭉칠 때가 아닙니다. 흩어져야 삽니다. 마음만은 모읍시다.",
  "keyword": [],
  "agree": 1392,
  "status": "청원종료"
}