{
  "time": "2020-10-20 05:00:08",
  "begin": "2020-02-26",
  "end": "2020-03-27",
  "category": "보건복지",
  "title": "판매용이 아닌 기업 자체 소비용 보건용 마스크 수입요건확인 면제요청 (긴급)",
  "content": "기업자체 사용용도 보건용 마스크 수입요건확인 면제(긴급) 청와대국민청원을 긴급하게 올립니다. 서울 강남구 언주로의 **관세법인 상무를 담당하고 있는 관세사입니다. 판매용이 아닌 기업에서 직원들과 그 가족들에게 공급하려고 하는 보건용 마스크에 대해 2020년 3월말까지 한시적으로 약사법상 요건확인면제를 확인서 없이 통관할 수 있도록 식품의약품안전청장이 지침을 내릴 수 있도록 정부에서 직접 지시해 주시기 바랍니다. (애로사항) 보건용 마스크를 기업에서 자가 소비용으로 수입하고자 할 경우 요건면제 확인관련 어느 조항에도 해당하지 않아 지방 식품의약품안전청에서는 면제가 불가능하다는 답변을 하고 있습니다. 지금 한국의 코로나19확산으로 해외의 관계회사와 협력회사들이 국내 회사들의 직원들과 그 가족들을 위해 무상으로 마스크를 보내주려고 하고 있습니다. 지난 주에는 우리나라에서 중국의 많은 협력회사에 마스크를 보내기도 했습니다만 보건용 마스크와 수술용 마스크는 약사법에 의해 한국의약품수출입협회장의 표준통관예정보고서를 받은 후에 수입할 수 있습니다. 지금 일반인이 사용하는 마스크는 보건용 마스크입니다. 해외의 동일한 제조자가 만든 물품이라도 표준통관예정보고를 받으려면 3백만원정도의 비용과 시험검사 및 승인까지 한달 이상 소요될 겁니다. 이러한 상황에서는 세관통관을 위해서는 표준통관예정보고서를 받아야 하고, 면제를 받기 위해서는 식품의약품안전청장의 면제확인서를 받아야 합니다. 그런데, 수입요건확인면제의 범위와 추천대상에는 이러한 CASE는 해당되지 않도록 규정하고 있습니다. 이제까지 식품의약품안전처에서도 이런 상황은 예상하지 못했으니까요? 세관을 통관하지 못한 마스크와 해외에서 보내려고 해도 통관이 되지 않을 것으로 예상되어 보내지 못하고 있는 마스크가 많이 있습니다. (건의사항) 1. 2020년 3월까지 한시적으로 보건용 마스크에 대해 판매용이 아닌 기업에서 회사직원들과 그 가족들에게 나누어주려고 해외 협력회사들에서 구해서 보내 주는 보건용 마스크에 대해서는 수입요건확인면제 확인서가 없이도 통관되도록 식품의약품안전청장이 지침을 내려주시기 바랍니다. 관세청은 약사법을 관할하는 기관과 협의없이 독자적으로 통관을 허용할 수 없으니까요. 식품의약품안전청장 관련부서에서 수출용 마스크의 단속에 집중하고 있어서 바빠서 수입용 마스크의 수입요건면제에 대한 지침을 시행하자고 협의할 수도 없는 상황입니다. 세관 수입과에 많은 문의가 오고, 기업들에도 해외에서 보내주겠다고 연락이 많이 오고 있습니다 (참고사항) 불과 지난 주만해도 한국의 상황이 심각하지 않아 다수의 마스크가 국내 기업들에서 중국의 관계사로 수출되었는데 중국에서는 쉽게 통관되어 잘 사용하고 있다고 합니다. 이러한 관계부처 협의는 공무원끼리는 쉽게 할 수 없습니다. 법을 어기는 것이기 때문입니다. 그러나 법도 다 사람이 살자고 만들어 놓은 것입니다. 긴급 확인후에 조치를 바랍니다. 규정을 모르시면 관세청 통관기획과자장과 협의바랍니다. [본 게시물의 일부 내용이 국민 청원 요건에 위배되어 관리자에 의해 수정되었습니다]",
  "keyword": [],
  "agree": 588,
  "status": "청원종료"
}