{
  "time": "2020-10-20 05:08:36",
  "begin": "2020-03-03",
  "end": "2020-04-02",
  "category": "인권/성평등",
  "title": "초,중,고 개학연기및 방학감소",
  "content": "지금 코로나19로인한 개학연기및 방학감소라는 안건은 불합리하다고 생각합니다 왜냐하면 첫번째로 저희가 학교를 안가고싶어서 가는것도아닌데 불합리하게 이로인한 방학감소 수업일자를 채우기위하여 방학을감소시키는것은 좋지않다고 생각합니다 왜냐하면 일단 여름방학,겨울방학을 감소시키면 무더운 여름날 에어컨을 틀어도 덥고 찝찝한 날씨에 한반에 여럿이서 수업을듣는다는것은 서로에게도 짜증나고 불쾌지수만 높아질뿐입니다 더군다나 원래는 오지않을 시기에 학생들이 학교를 옴으로써 냉난방비도 더 많이 들것입니다 그럼 자연스레 예산낭비를하게될것이고 정작필요한곳에 예산을쓰지못할수있는 일이 일어날수있습니다 그리고 추운겨울날에도 마찬가지로 난방비가 무지들어갈텐데 그것을 충족시켜줄 예산을 또다시 얻어와야하기때문에 그것도 전국의 초중고 학교들이 냉난방비를 소비를 시켜버리면 지구온난화는 물론 막대한예산소비로 돈낭비만 해버리는 사태가 일어날것이라고 생각합니다 그리고 학생들의 의견은 듣지않고 어른들끼리 저희의 입장과 상태를 판단하여 이런 행동을 하는것은 저희가 어른들께반감만 조성할뿐입니다 이점 고려해주셔서 저희의 입장도 생각을해주셨으면 하는 바램입니다.",
  "keyword": [],
  "agree": 234,
  "status": "청원종료"
}