{
  "time": "2020-10-20 05:27:15",
  "begin": "2020-03-24",
  "end": "2020-04-23",
  "category": "외교/통일/국방",
  "title": "아들(군인)에게 영화나 다큐멘타리 같은 콘텐츠를 보낼 수 있게 해주세요",
  "content": "안녕하세요. 사랑하는 아들을 군에 보낸지 벌써 8개월이 넘은 아빠입니다. 제가 군생활 할때에 비하면 상당한 수준의 자유와 복지가 보장된다는 말에 부모 입장에서는 크게 안심이 됩니다. 아들녀석도 꽤 잘 적응하고 있다는 전화를 받고 있습니다. 그러나, 최근 코로나19의 확산방지를 위해 사회적 거리두기 캠페인을 벌이고 있어 외출이나 타인과의 접촉을 최소화하고 있습니다. 이 때문에 군에서는 외출, 외박, 휴가 등이 모두 통제되고 있으며, 이로인해 아이들은 병영생활이 답답함을 느끼고 있다고 합니다. 부모의 마음은 아이들이 안전하고 건강하게 군복무를 마치는 것입니다. 아들에게 물어보니 생활관에 설치된 TV에서는 제한적인 영화나 다큐멘터리를 시청할 수 있을 뿐 최신 영화 등은 볼 수 있는 방법이 없다고 들었습니다. 휴일, 주말 등 자유시간에 즐거움과 위로가 될 수 있도록 병영생활 개선을 위해 건의드리오니 시행될 수 있도록 도와주세요. 1. 부모가 아들(병사)에게 영화나 다큐멘터리 등을 선물 할 수 있게 해주세요. 2. 아이들이 부모가 선물한 콘텐츠를 TV나 휴대폰을 통해 시청할 수 있게 해주세요. 제 아들, 앞으로 이 나라를 위해 복무해줄 미래의 자식들이 군생활에 좀더 잘 적응할 수 있는 방법을 연구해주시기 바랍니다.",
  "keyword": [],
  "agree": 264,
  "status": "청원종료"
}