{
  "time": "2020-10-20 05:33:26",
  "begin": "2020-03-30",
  "end": "2020-04-29",
  "category": "정치개혁",
  "title": "변호사시험과 판사 ㆍ검사시험을 구분실시",
  "content": "<변호사시험은 공인중개사 시험과 함께 실시해야 전화변론등 사법농간을 방지할 수 있습니다> 왜냐하면 학력제한없이 누구든지 응시할 수 있는 사법시험을 부활하여 임용한 판사 ㆍ검사는공무원입니다. 따라서 변호사는 공무원이 아닌 민간자격증이므로 민간자격시험인 공인중개사ㆍ세무사ㆍ변리사ㆍ행정사 ㆍ법무사 등 시험과 같이 사법시험과 별도로 변호사시험을 시행해야 사법적폐를 청산할 수 있습니다. 사법시험에 합격하여 임용된 판사ㆍ검사는 국가공무원 이므로 공인중개사와 같은 민간자격증인 변호사를 할 수 없기때문에 전관예우도 자동폐지됩니다",
  "keyword": [],
  "agree": 277,
  "status": "청원종료"
}