{
  "time": "2020-10-20 06:04:04",
  "begin": "2020-05-17",
  "end": "2020-06-16",
  "category": "기타",
  "title": "대형할인마트 긴급재난지원금 사용할수있도록 도와주세요",
  "content": "안녕하세요 저는 남들이 쉬는 주말에도, 코로나로 손님이 한 명도 없어도 출근해야하고 하루 14시간씩 근무하는 대형할인마트에 입점한 의류매장운영중입니다 그나마 주말에 손님이 좀 있는가 싶더니 긴급재난지원금이 사용안된다는 말에 그마저도 손님들의 발길이 끊겼습니다 저희는 로드샵보다 매출에대한 마진이 절반이나 적습니다 대형할인마트 안에 있다는 이유로 선불카드가 되지않아 손님들도 저희들도 모두 안타까워 한숨만 쉽니다 코로나가심각할때는 하나도 못팔그 14이간을 꼬박 근무하고 지금은 긴급재난지원금 사용이 안되서 주말에도 손님이 없어 너무 힘듭니다 한달급여로 최저임금만큼이라도 받고 싶습니다 사업자가 없는 종합소득세 신고하는 수수료매장이라는 이유로 소상공인 이자없는 대출도 못받았습니다 긴급재난지원금이라도 사용가능하게 해주세요 고객님들이 다시 찾아줄수있도록 도와두세요 생활비가 이제는 감당이 안됩니다 도와주세요",
  "keyword": [],
  "agree": 1298,
  "status": "청원종료"
}