{
  "time": "2020-10-20 07:22:18",
  "begin": "2020-09-18",
  "end": "2020-10-18",
  "category": "교통/건축/국토",
  "title": "국가와 건축사협회는 각성해야 합니다.",
  "content": "국가와 건축사협회는 각성해야 합니다. 건축사로서의 전문성을 갖추기 위하여 황금 같은 시간과 노력을 투자하여 경력을 쌓고 시험 준비를 하여 건축사자격을 취득하였건만 국가와 협회는 외부 세력들의 의견만을 받아들여 건축사가 무슨 기득권 세력인 것 마냥 제동장치도 없이 손바닥 뒤집듯이 전문직에 대한 터무니없는 정책을 펼치고 있습니다. 우리나라가 사회주의 국가입니까? 앞으로 국가를 믿고 앞날을 위하여 무엇인가에 시간과 노력을 투자하겠습니까? 국가 정책을 선심 쓰듯이 써도 되는 것입니까? 정책의 섬세함은 찾아볼래야 찾아볼 수가 없습니다. 법은 일단 만들어놓고 아니다 싶으면 다시 만들면 되나요? 현업에 종사하는 전문가들의 의견을 수렴하여 합리적이고 체계적인 계획하에 법을 제정하고 순차적으로 정책을 펼친다면 누가 뭐라고 하겠습니까? 불과 1,2년 전까지 어렵게 자격을 취득한 사람들은 바보들인가요? 임기 동안에 나라를 완전히 뜯어고칠 계획이신가요? 일자리 창출이 아닌 하향 평준화를 원하시나요? 건축사는 전문성과 책임이 막중한 직업입니다. 부디 전문직 수를 늘리려거든 장기적 안목을 가지고 피해를 최소화할 수 있도록 순차적으로 정책을 펴나가길 바랍니다. 이에 제안합니다. 1. 2026년 12월 31일까지는 기존 시험제도 및 합격률로 되돌려 주십시오. 2. 5년제 건축과 학생들만 시험에 응시할 수 있는 2027년 01월 01일부터는 부실 건축학과는 퇴출시키고 국가에서 숫자를 관리는 건축사 면허제도를 도입해 주십시오.",
  "keyword": [],
  "agree": 153,
  "status": "청원종료"
}