{
  "time": "2020-10-20 07:22:38",
  "begin": "2020-09-18",
  "end": "2020-10-18",
  "category": "행정",
  "title": "개인택시들이 받는 2차 재난지원금 법인택시 운전자들에게도 지급해 주세요.",
  "content": "저는 경주에서 법인택시를 운행하는 택시운전자입니다. 2차 재난지원금 대상에서 핀셋 족집게로 콕 집혀서 재난지원금 대상에서 제외 대상이 되었네요. 2차재난지원금 대상자들 중에는 개인택시를 하시는 분들은 소상공인으로 포함되어 1차에 이어 2차에도 대상이 되어 지원금을 받는다고 합니다. 승객이 감소하여 매출이 줄어든 개인택시 분들이 지원을 받는 것도 당연합니다. 그 것이 배가 아픈 것이 아니라 그들보다 더 어렵고 힘든 법인택시 운전자들이 대상에서 제외되었다는 것이 슬픕니다. 요즘 개인택시를 하려면 최소 1억이라는 돈이 있어야 면허를 살수가 있습니다. 그 놈의 1억이 없어 법인택시를 하고 있는 법인택시 운전자들이 그들보다 살림이 나아서 지원을 안 해 주겠지요. 설마 정부가 핀셋 운운하면서 맞춤형 지원이라고 했는데 개인택시들이 법인택시 운전자들보다 살림이 나으면 말이 아니지요? 제가 택시를 한지도 30년이 다되어가네요 그럼에도 하루 하루 살아가기 급급하여 개인택시를 사야겠다는 마음조차 가질 여유가 없는 팍팍한 살림살이로 힘겹게 버티고 살아가지만 공정을 운운하는 현 정부의 미흡한 정책 결정으로 보다 힘들고 소외된 계층이나 사람들이 있다면 이는 현 정부의 능력이 부족한 것이겠지요? 개인택시보다 더 절실한 법인택시 노동자들에게 희망을 주시기를 청원합니다.",
  "keyword": [],
  "agree": 3730,
  "status": "청원종료"
}