{
  "time": "2020-10-20 05:12:52",
  "begin": "2020-03-06",
  "end": "2020-04-05",
  "category": "경제민주화",
  "title": "긴급국가재난 소상공인 임대인 특별법 만들어주세요!",
  "content": "저는 법은 잘 모르는 교육업에 종사하는 30대 여성입니다. 하지만, 옳고 그름 상식은 누구나 판단 하실 수 있을거라 믿습니다. '착한건물주' 라는 슬로건으로 이슈가 되어 올바른 상식으로 동참 하는 건물주분들도 많지만, 그렇지 않은 분들도 많습니다. 국가재난 상태인 코로나19 사태로 많은 소상공인 분들이 어려움속에서도 함께 동참해 주시는 분들이 대 다수 인걸로 알고 있습니다. (저 또한, 휴원중이고 교육비도 받지 못하고 있습니다.) 나라 세금으로 이 모든 소상공인들을 지원한들 언제 어떻게 어느정도의 금액으로 힘이 될 수 있을지 불안감만 앞섭니다. 물론, 매출이 크고 잘 되는곳은 여전히 성업중이지만, 대 다수 하루살이로 먹고 사는 소상공인들이 많습니다. 저 또한 벌어서 월세 내기 급급한 상황에 코로나19가 터져 월세를 낼수없는 실정에 있습니다. (저희 주인은 콧방귀를 끼시더군요ㅎㅎ) 전쟁이나도 월세 입금하라 독촉하실껀가요? 앞으로도 코로나 19 로 재난이 끝날리 없을거라 생각됩니다. 긴급 특별법을 마련해주십시오! (예를들어, 국가재난상황에서 월세 반값) 국민들이 낸 세금은 한푼도 어김없이 공무원들에게 돌아가면서 왜 그 짐은 하루벌어 하루먹고사는 소상공인들의 몫이 되어야합니까! 이것이 민주주의 맞습니까? 휴원은 권고하면서 월세도 세금도 모두 다 받아가고 빚을 조장하는 현, 상황에 정말 화가납니다. 모두가 상생하는 대한민국이 되었으면 합니다. 급하게 두서없는 글 읽어주셔서 감사합니다. 많은 청원 부탁드립니다!",
  "keyword": [
    "특별법",
    "긴급",
    "국가",
    "월세",
    "소상",
    "공인",
    "상공",
    "상황",
    "하루",
    "재난"
  ],
  "agree": 296,
  "status": "청원종료"
}