{
  "time": "2020-10-20 05:09:54",
  "begin": "2020-03-03",
  "end": "2020-04-02",
  "category": "경제민주화",
  "title": "부동산 규제보단 한시적으로라도 공매도 금지해주세요",
  "content": "19차례 부동산 대책동안 부동산은 폭등을 거듭하고 있습니다. 대한민국에서 돈을 벌려면 부동산을 하라고하죠. 공무원시험은 사상 초유의 경쟁률을 기록하고 자영업자들은 폐업을 거듭하고 있고 직장인들은 출근할때면 언제 본인의 책상이 없어질지 모르는 퇴직의 압박갑에 매일을 고통받고 있습니다. 투자는 나쁜것일까요? 투기가 아닌 투자는 독려되어야합니다. 코로나19의 영향으로 최근 코스피 지수가 2000아래로 곤두박질쳤습니다. 2011년 2100이었던 코스피지수가 부끄러운 박스피라는 꼬리표를 단채 전혀 발전이없고 개인투자자들 소액주주들 흔히 개미들이라 불리는 서민들 곡간만 거들나고 있습니다. 한시적으로라도 공매도 금지시켜주세요. 주식시장이 건전해진다면 부동산에만 몰려있는 자금이 자연스럽게 주식시장으로도 분산되고 부동산 폭등을 막을수있지 않을까요!",
  "keyword": [
    "부동산",
    "투자",
    "주식시장",
    "지수",
    "폭등",
    "코스피",
    "거듭",
    "언제",
    "대한민국",
    "퇴직"
  ],
  "agree": 2135,
  "status": "청원종료"
}