{
  "time": "2020-10-20 05:13:30",
  "begin": "2020-03-06",
  "end": "2020-04-05",
  "category": "보건복지",
  "title": "7세미만 아동이 아니라 18세 이상 어른에게 상품권을 지급해주세요",
  "content": "7세미만 아동수당을 받는 가정에 월 10만원씩 4개월간 지역사랑 상품권을 지급하는 추경이 이루어지고 있다는 기사를 보았습니다 저는 홀로 세아이를 키우고있는 엄마 입니다 막내 아이는 올해 5살로 아동수당을 받고 있고 두아이는 초등학생으로 집에서 세아이 모두 보육중입니다. 월에 10만원이 적은 돈은 아닙니다 아이들 식비로 이미 기존생활비보다 많은 지출이 있지만 자영업을 하는 아이 아버지의 수입은 거의 없는 지경이라 양육비도 받지 못하고 있습니다 이런 시기에 저 금액이 큰 도움이 되리라는건 알고 있지만 형편성에 맞지 않는 혜택이라 생각 됩니다 시장경제의 활성화를 위한 대책이라지만 7세 미만 자녀가 있는 가정만 힘든것은 아닙니다. 이미 많은 자영업자들이 도산 위기에 처해있고 그분들의 대부분은 현재 40대 중 고등학생 자녀를 키우는 중년인경우가 많습니다 국가 경제의 위기로 시장 활성화를 위한 추경이라면 아동에게 국한된것이 아니라 모든 국민이 혜택을 보아야 한다고 생각합니다 만 18세 이상의 어른들에게 10만원씩 두달간 지원을 해주세요. 아이가 없는집은 있지만 어른이 없는집은 없습니다. 어른이 있어야 아이를 키우니까요. 아이들이 우리의 미래이지만 현재의 경제를 부흥하고 소비의 주축이 되는것은 만 18세 이상의 성인입니다",
  "keyword": [
    "아이",
    "아동",
    "어른",
    "경제",
    "가정",
    "현재",
    "활성화",
    "이상",
    "자영",
    "생각"
  ],
  "agree": 723,
  "status": "청원종료"
}