{
  "time": "2020-10-20 05:17:23",
  "begin": "2020-03-12",
  "end": "2020-04-11",
  "category": "교통/건축/국토",
  "title": "야간 전조등 끄고 달리는 '스텔스'차량 처벌 강화해주세요.",
  "content": "안녕하세요. 경기도에 거주하고 있는 직장인입니다. 저는 자차로 출퇴근을 하고 있습니다. 교대근무를 하기 때문에 새벽에도 운전을 하게 되는데 밤에는 어두운 만큼 시야확보가 잘 안되기 때문에 자동차의 전조등을 켜야만 합니다 하지만 가로등도 없는 곳에서 차량의 전조등을 켜지않고 다니는 차량들이 많이 보입니다. 이를 부르는 용어가 바로 스텔스(Stealth) 차량 입니다. 등화가 점등되지 않은 차량은 도로에서 위험한 물체가 될 수밖에 없습니다. 저도 실제로 사고당할 뻔한 적도 있고, 제 주변에서도 목숨을 잃을 뻔한 사고도 있었습니다, 스텔스 차량으로 인한 사고 사망률도 일반 추돌 사고 대비 약 300%에서 많게는 900%가 더 높다고 합니다. 사고가 많이 나는 이유는 스텔스 차량의 존재를 인지하지 못했기 때문에 위급한 상황에서 속도를 줄이거나 피할 겨를이 없기 때문입니다. 물론 이를 위반했을때 처벌 규정은 벌점없이 승합차와 승용차는 2만 원,이륜차는 1만 원의 범칙금이 부가되긴 하지만 이렇게 금액이 낮기 때문에 전조등을 확인하는 운전자가 많지 않은 거 같습니다. 미국은 벌금이 꽤 높다고합니다. 적게는 30만 원, 많기는 100만 원까지 부과됩니다. 미국처럼은 아니더라도 처벌을 강화하거나 안전교육을 더 강화해서 이러한 사고를 꼭좀 막았으면 합니다.",
  "keyword": [
    "차량",
    "사고",
    "때문",
    "스텔스",
    "전조등",
    "처벌",
    "운전",
    "미국",
    "도로",
    "이륜차"
  ],
  "agree": 635,
  "status": "청원종료"
}