{
  "time": "2020-10-20 05:18:07",
  "begin": "2020-03-13",
  "end": "2020-04-12",
  "category": "행정",
  "title": "코로나19 바이러스 재난위기 건강보험료 감액요청",
  "content": "저는 자영업자입니다 2월달 매출이 100만원이하로 떨어졌는데 3월달 매출은 12일인 오늘까지 0원입니다 그러나 작년 연수익이 1,800만원이어서 매달 건강보험료로 38만원을 납부하고 있습니다 직장인 연봉 1억에 해당하는 월 건강보험료가 277,910원입니다 연수익 1,800만원이면 월수익150만원인데 직장인 월실수령액 150만원의 건강보험료는 55,580원입니다 이것이 정상적이고 공평한 산출방법인가요? 직장인보다 7배를 더 내고 있는것입니다 현재 매출이 0원이라 한끼 먹는것도 힘든데 관리비며 지출을 아무리 아껴도 코로나바이러스가 언제 끝날지도 모르고 언제까지 버틸수 있을지도 모르겠습니다 가장 부담스러운건 건강보험료 38만원 납부인데 자영업자의 보험료 산출방법에 문제가 많을뿐만 아니라 대한민국 모든 자영업자들은 건강보험료 산출방법이 정당하다고 느끼는 사람은 없다고 단언합니다 정책은 소통하고 지지받아 이뤄져야 하는데 일방적이고 강압적으로 이뤄져서는 국민의 신뢰를 얻을수 없습니다 현재 전세계적으로 바이러스로 인해 경제가 무너지고 있는데 보험료산출방법을 바꾸지 않으면 매출없는 자영업자들의 폐업이 속출할수 밖에 없는 상황이 될것입니다 지금 당장 바꿀수 없다면 바이러스사태가 끝날때까지 만이라도 50%감액을 해주실것을 청원합니다 참고로 저는 병원을 1년에 한두번 정도밖에 이용하지 않습니다 치과 스케링이나 피부 트러블땜에 연고 처방받는 정도가 다입니다 많이 가는 사람에겐 보험료증액이, 적게 가는 사람에겐 감액을 해줘야 형평성이 맞는거 아닌가요? 1. 당장은 자영업자들이 지금의 재난을 버틸수 있게 보험료 감액을 요청합니다 2. 재난이 지나고 나면 형평성에 맞게 다시 건강보험료 산출 방법을 조정해 주셔서 국민 모두가 공평하게 건강보험료가 납부 되어지길 바랍니다",
  "keyword": [
    "코로나",
    "보험료",
    "재난",
    "건강",
    "방법",
    "자영",
    "산출",
    "업자",
    "매출",
    "바이러스"
  ],
  "agree": 572,
  "status": "청원종료"
}