{
  "time": "2020-10-20 05:22:37",
  "begin": "2020-03-20",
  "end": "2020-04-19",
  "category": "기타",
  "title": "대학 등록금",
  "content": "국가를 넘어서 전세계가 전염병 코로나 19사태로 사회가 악화되어 초.중.고등학교는 물론이고 대학까지 오리엔테이션과 입학식은 물론 각종 행사까지 취소되고 개강까지 늦춰가며 코로나19 사태에 피해를 보고 있습니다. 동참하는 바가 맞겠지만 솔직히 학생들이 학교나 교육청에 건의를 한 것도 아니고 개강시기를 1달 늦춰간다고 해도 확진자가 안나오는 것도 아닐것이고 사이버 강의, 강의를 대신해 과제를 해가는 4월 초 개강 대학은 3월 1달의 대학등록금에 대해 환불신청 청원합니다.",
  "keyword": [
    "등록금",
    "대학",
    "개강",
    "코로나",
    "사태",
    "강의",
    "학교",
    "청원",
    "간다",
    "취소"
  ],
  "agree": 911,
  "status": "청원종료"
}