{
  "time": "2020-10-20 05:46:27",
  "begin": "2020-04-13",
  "end": "2020-05-13",
  "category": "정치개혁",
  "title": "재외공관 개표 금지",
  "content": "선거는 민주주의의 꽃이라고 합니다. 그 이유는 대한민국 헌법 제1조2항: 대한민국의 권력은 국민에 있고, 모든 권력은 국민으로부터 나온다. 즉, 국민으로부터 위임받은 권력에 대한 정치인들의 활동과 정책을 평가함으로써 국민의 삶과 자유민주주의 가치를 지켜나 가는 중요한 국민의 권리이기 때문입니다. 따라서, 선거의 공정성과 투명성, 신뢰성은 선거의핵심이며... 선거운동 및 선거 투개표 과정에서 한치의 의혹이나 논란이 야기될 사항들을 관리하고 예방하는 것은 정부의 의무인 것 입니다. 허나, 재외국민의 개표를 재외공관에서 실시 한다는 것은 개표의 신뢰성을 회손 하는 민주주의를 파괴하는 행위 입니다. 코로나19로 항공편이 어려워 부득이 내린 결정이라는 말은 핑계에 불과한 것 입니다. 국민의 혈세로 마련된,대한민국 공군이 보유한 수송기가 몇대이며, 수 많은 항공사가 보유한 비행기가 몇대인데.. 19개국 공관의 투표함조차 국내로 수송할 능력이나 외교력이 없다면 이는 나의 자랑 스런 조국 대한민국이 아닙니다. 해외 공관에서의 개표의 공정성, 신뢰성 을 어떻게 담보 하나요? 국민은 절대로 신뢰할 수 없습니다. 따라서, 불필요한 국론의 분열과 갈등을 개표의 불법에 휘말리지말고... 국민의 소중한 한표가 제대로된 가치를 보장할 수 있도록 해외공관의 투표함을 국내로 이송하여, 각 정당의 개표감시원 의 참관하에 공정하고 투명한 개표가 될 수 있도록 청원 합니다.",
  "keyword": [
    "금지",
    "개표",
    "재외공관",
    "국민",
    "대한",
    "선거",
    "대한민국",
    "공관",
    "신뢰",
    "민주주의"
  ],
  "agree": 414,
  "status": "청원종료"
}