{
  "time": "2020-10-20 06:48:14",
  "begin": "2020-07-27",
  "end": "2020-08-26",
  "category": "교통/건축/국토",
  "title": "법인 종합부동산세 최고세율 적용은 부당합니다.",
  "content": "저는 주택 매매업, 임대업을 업종 코드로 하여 법인을 설립했습니다. 설립했을 당시 법인으로 매매와 임대를 하는 것은 불법이 아니었습니다. 지금도 현행 법상 불법이 아닙니다. 법인은 개인보다 많은 제약을 가지고 있습니다. 사무실 임대료, 세무기장비, 법인세 조정료, 성실신고료 등 이 모든 것을 합하면 1년에 운영비로만 최소 5백만원의 비용이 소요됩니다. 취등록세의 경우에도 개인보다 중개수수료 비용등을 가산하여 세금이 부과되기에 더 많은 비용을 내고 있습니다. 법인으로 번 돈도 마음대로 쓸 수 없었습니다. 그 돈은 사업을 위해 써야 하는 돈이니까요. 개인들은 다운계약서도 자유롭게 쓴다지만, 법인은 투명하게 운영해야 하기 때문에 모든 것을 법 테두리 안에서 정직하게 운영했습니다. 법인의 돈은 벌어도 내 돈이 아닌 것입니다. 수익으로 다시 가져올 때는 15.4%의 세금을 떼고 다시 종합소득세의 이중과세도 납부해야 합니다. 사업외의 목적으로는 경비처리도 어렵습니다. 임대차 계약에 있어서도 개인들보다 최소 2~3천은 낮은 전세가로 제공하여 저렴한 임대를 진행했습니다. 저는 법인에서 만들어진 수익으로 세상에 기부도 많이 하였고 수익을 가지고 사업을 만들려고 준비도 하고 있었습니다. 그런데, 이번에 종합부동산세 3%, 6%가 부여된다고 하고 유보소득에 대해서 과세를 한다고 하여 사업체를 만들어 보고자 했던 저의 꿈도 접어야 합니다. 사업기반 자금을 모두 세금으로 내어야만 하니까요. 종합부동산세는 징벌적 과세가 아니라 그 취지가 고가 주택에 대해서 일정 과표기준을 초과하면 내는 세금으로 알고 있습니다. (법인은 이미 국가에 정직하게 많은 세금을 내고 있습니다. ) 지금도 법인에 부과되는 세금은 적지 않습니다. 법인은 돈을 마음대로 융통할 수 없고, 수익이 난 부분을 배당받아 돈을 꺼내오려해도 기타 많은 세금을 내어야 해서 개인보다 불리하기 때문입니다. 법인이 경제 활성화에 도움이 되지 않는 것이 아닙니다. 법인은 경비를 사용하면서 개인보다 많은 소비를 하게 됩니다. 다시 사회에 환원되는 것이죠. 법인도 국민입니다. 법인도 사회에 일조하는 부분이 많이 있습니다. 주택문제에 대해 정부가 많은 우려를 하고 있음을 알고 있습니다. 법인으로 인해 지방 미분양 물건이나 지방 경기가 활성화 되었던 측면도 감안해 주시기 바랍니다. 국가 균형발전에서 만약 이대로 법안이 통과되어 진행된다면, 서울 수도권은 모르겠지만 지방의 경우에는 많은 아픔이 있을 것 같습니다. 전문가 분들이셔서 더 잘 아시겠지요... 법인 종부세 상한 폐지, 종부세율 최고세율 적용은 종합부동산세의 취지상 위헌이라고 생각합니다. 부디 이번 법인 종부세 법안을 재고해 주시기를 청원합니다.",
  "keyword": [
    "법인",
    "세금",
    "개인",
    "임대",
    "사업",
    "종합",
    "수익",
    "부동산",
    "지방",
    "비용"
  ],
  "agree": 1221,
  "status": "청원종료"
}