{
  "time": "2020-10-20 06:54:41",
  "begin": "2020-08-07",
  "end": "2020-09-06",
  "category": "안전/환경",
  "title": "음주운전 사고 강력 처벌을 원합니다.",
  "content": "음주운전 사고 강력 처벌을 원합니다. 07월 05일 새벽 06시 05분 ** ** 하행선에서 음주차량으로 인한 인명피해 사고가 있었습니다. 한 번쯤은 괜찮겠지라는 안일한 생각으로 가해자는 운전대를 잡았겠지만, 그 행동으로 인해 두 가정이 무너졌습니다, 아버지의 40년 지기 친구분은 사고 현장에서 돌아가셨고 제 아버지는 중환자실에서 수술도 못한 채 누워계십니다. 한 달이 다 되어가는 이 시간에도 가해자는 사과 한 번 없고 장례식장에도 얼굴을 비추지 않았습니다. 음주운전은 잠재적 살인행위와 다름없습니다. 해외에서도 이러한 사례로 인해 차량 강제매각, 한달 급여 몰수, 종신형, 심하게는 사형에까지도 처벌의 수위를 정해놓고 있음을 알고 있습니다. 이 사건에 가해자는 한 달이 다 되어가는 이 시간 동안 구속도 안된 상태입니다. 담당 경찰 수사관님에게 전해 들은 얘기로 과속 여부를 확인하기 위해 국과수에 의례한 상태고 결과에 맞춰서 검찰청에 구속영장 발부한다고 들었습니다. 현재 가해자는 다니던 회사에서 권고사직된 상태고 공황장애로 인해 정신과를 다닌다는 말을 전해 들었습니다 지금 다니던 직장을 잃은 건 중요하지 않습니다. 구속이 현재까지도 이뤄지지 않은 것에 너무 어이가 없고 가해자는 그 어떠한 사과 조치도 안 하고 있다는 것에 괘씸함이 밀려옵니다. 다시는 이러한 일이 생기지 않도록...더욱 경각심이 들도록 이사건으로 인해 다른 피해자가 더 이상 생기지 않도록 엄중한 처벌을 요구하는 바입니다. [본 게시물의 일부 내용이 국민 청원 요건에 위배되어 관리자에 의해 수정되었습니다]",
  "keyword": [
    "가해자",
    "음주",
    "사고",
    "상태",
    "처벌",
    "구속",
    "차량",
    "현재",
    "생기지",
    "사과"
  ],
  "agree": 1903,
  "status": "청원종료"
}