{
  "time": "2020-10-20 07:13:05",
  "begin": "2020-09-03",
  "end": "2020-10-03",
  "category": "기타",
  "title": "최대집씨가 회장으로 있는 대한의사협회의 해체를 요구합니다!",
  "content": "나라가 어려움에 모두 힘을 합쳐 이 상황을 이겨나가도 모자랄 판에 그 어려움을 배가 시키는 요즘 대한의사협회를 이해할 수가 없었습니다. 그러나 이 영상을 보고... '아! 이건 사람이면 이해할 수가 없었던 게 맞구나!'라는 걸 알았습니다. 이런 인격을 지닌 사람이 회장으로 있는 협회라니.. 이런 사람이 대표해서 목소리를 내는 집단이었으니 보통의 상식을 가진 사람이라면 이해할 수가 없는 것이었습니다. 나라에 해악을 끼치는 이 집단의 해체를 강력하게 요구합니다! 대다수 정상적인 사람의 목소리가 앞설 수 있는 나라를 만들어주세요!",
  "keyword": [
    "사람",
    "이해",
    "수가",
    "나라",
    "어려움",
    "협회",
    "집단",
    "목소리",
    "해악",
    "정상"
  ],
  "agree": 4598,
  "status": "청원종료"
}