{
  "time": "2020-10-20 07:17:36",
  "begin": "2020-09-11",
  "end": "2020-10-11",
  "category": "행정",
  "title": "범죄를 조사하는 현장이 범죄의 현장이 되지 않도록 제도를 만들어 주시기를 부탁드립니다.",
  "content": "“경북체육회, 경주시청, 경주경찰서 그 누구도 故 최숙현 선수의 말에 귀를 기울여 주지 않았다.” 故 최숙현 선수의 죽음이 헛되지 않도록 다음을 주장합니다. 1) 조사관에 의하여 인권이 유린당하고 범죄가 조작되지 않도록 모든 형사 사건의 조사는 녹화해야 한다. (범죄를 조사하는 현장이 범죄의 현장이 되지 않도록 해야 한다. 조사관에 의하여 범죄의 은폐, 축소, 조작, 심지어 증거를 인멸하는 일도 발생하고 있다.) 2) 경찰서의 모든 통화 내용은 녹음하여 2년 이상 보관하여야 한다. (서비스 업종에서도 녹음하고 있다. 하물며 경찰서는 거대한 공권력이다. 고소인과 피고소인, 담당공무원 모두를 위한 안전장치가 될 수 있다.) EX 01) 고최숙현 선수에게 가혹 행위를 했던 사람들이 구속기소 되었다는 뉴스를 보았다. sports W 뉴스 2020-07-01 뉴스에 보면 “경북체육회, 경주시청, 경주경찰서 그 누구도 故 최숙현 선수의 말에 귀를 기울여 주지 않았다.”라고 주장했다. “경주경찰서 역시 무성의하게 조사를 마치고는 사건을 검찰에 이첩 시켰다는 것이 이의원측의 주장이다.”라고 나온다. 故 최숙현 선수는 자신을 괴롭히던 사람들을 체육 단체에 그리고 경주시청에 알린 까닭은 자살하려고 했던 것이 아니라 살고자 했던 것은 아닐까? 체육 단체나 경주시청에서 아무런 조치가 없었을 때 故 최숙현 선수는 최후의 보루로 사법기관에 신고하였을 것이다. 만약 조사관이 철저하게 조사하여 억울한 일이 없도록 했다면 죽음을 선택하였을까 하는 의문이 든다. 조사관이 사건을 은폐, 축소한다는 생각이 최 선수로 하여금 극단적 선택을 하게 한 것은 아닐까? EX 02) 이춘재 8차 사건에서도 억울한 옥살이를 한 윤모씨의 경우도 있다. 이 윤모씨는 얼마나 많이 자살을 생각했을까? 하는 생각과 함께 그의 삶의 무게가 필자에게 다가온다. 무죄가 밝혀졌다고 하니 참으로 다행이다. 그러나 그의 지나간 삶의 시간을 누가 보상할 것인가? EX 03) 또한 탈북자 월북에 대하여서 2020.07.27. SBS 뉴스를 보면 “이 남성을 잘 아는 사람은 월북할 가능성이 있다고 알렸는데도 경찰이 묵살했다고 주장했습니다.”라고 하였다. 필자는 경찰서에 통화되는 모든 내용은 최소한 2년은 저장되어야 한다고 생각한다. 필자는 거대한 공권력을 가진 조사관에 의하여 사건이 은폐, 축소, 조작되어 조사받는 고소인과 피고소인의 인권이 유린당하는 일이 발생하지 않도록 제도를 만들었으면 좋겠다.",
  "keyword": [
    "범죄",
    "현장",
    "시기",
    "조사",
    "경찰",
    "경주",
    "선수",
    "최숙현",
    "경찰서",
    "사건"
  ],
  "agree": 172,
  "status": "청원종료"
}